wavesynth.py
wavesynth-2.3.0.dist-info/licenses/LICENSE.txt
wavesynth-2.3.0.dist-info/METADATA
wavesynth-2.3.0.dist-info/WHEEL
wavesynth-2.3.0.dist-info/top_level.txt
wavesynth-2.3.0.dist-info/RECORD
