Metadata-Version: 2.4
Name: wavesynth
Version: 2.3.0
Summary: Simple sound-synthesis library for very basic music creation, intended for beginner programmers.
Home-page: https://cs.wellesley.edu/~pmwh/wavesynth/docs/wavesynth
License: BSD 3-Clause License
Classifier: Programming Language :: Python :: 3 :: Only
Classifier: License :: OSI Approved :: BSD License
Classifier: Development Status :: 4 - Beta
Classifier: Topic :: Multimedia :: Sound/Audio
Classifier: Topic :: Multimedia :: Sound/Audio :: Sound Synthesis
Classifier: Topic :: Education
Classifier: Intended Audience :: Education
Classifier: Intended Audience :: Developers
Classifier: Operating System :: OS Independent
Classifier: Natural Language :: English
License-File: LICENSE.txt
Provides-Extra: play
Requires-Dist: pyglet; extra == "play"
Dynamic: license-file
